{
  "count": 3,
  "items": [
    {
      "pureId": 9517632,
      "externalId": "77953800538",
      "externalIdSource": "Scopus",
      "uuid": "bfc570c3-10d8-451e-9145-c370d6f01c64",
      "title": "The Third Pure Publication",
      "peerReview": true,
      "numberOfPages": 16,
      "managingOrganisationalUnit": {
        "uuid": "937d604c-a16a-499d-80eb-bd6f931a343c",
        "name": [
          {
            "value": "School of Science (Behrend)"
          }
        ],
        "type": [
          {
            "value": "Department",
            "pureId": 855,
            "uri": "/dk/atira/pure/organisation/organisationtypes/organisation/department"
          }
        ]
      },
      "confidential": false,
      "info": {
        "createdBy": "root",
        "createdDate": "2017-01-10T21:31:33.124+0000",
        "modifiedBy": "sync_user",
        "modifiedDate": "2018-05-01T01:10:03.735+0000",
        "portalUrl": "https://pennstate.pure.elsevier.com/en/publications/bfc570c3-10d8-451e-9145-c370d6f01c64",
        "additionalExternalIds": [
          {
            "value": "77953800538",
            "idSource": "QABO"
          }
        ]
      },
      "totalScopusCitations": 32,
      "pages": "665-680",
      "volume": "30",
      "journalAssociation": {
        "pureId": 9517633,
        "title": {
          "value": "Journal of Vertebrate Paleontology"
        },
        "issn": {
          "value": "0272-4634"
        },
        "journal": {
          "uuid": "6bd3ad47-c2bf-44cb-9d79-85d9fe14550f",
          "name": [
            {
              "value": "Journal of Vertebrate Paleontology"
            }
          ],
          "type": [
            {
              "value": "Journal",
              "pureId": 910,
              "uri": "/dk/atira/pure/journal/journaltypes/journal/journal"
            }
          ]
        }
      },
      "journalNumber": "3",
      "type": [
        {
          "value": "Article",
          "pureId": 4664,
          "uri": "/dk/atira/pure/researchoutput/researchoutputtypes/contributiontojournal/article"
        }
      ],
      "category": [
        {
          "value": "Research",
          "pureId": 6885,
          "uri": "/dk/atira/pure/researchoutput/category/research"
        }
      ],
      "language": [
        {
          "value": "English (US)",
          "pureId": 9423172,
          "uri": "/dk/atira/pure/core/languages/en_US"
        }
      ],
      "abstract": [
        {
          "formatted": true,
          "value": "<p>This is the third abstract.</p>"
        }
      ],
      "totalNumberOfAuthors": 5,
      "openAccessPermission": [
        {
          "value": "Indeterminate",
          "pureId": 3436171,
          "uri": "/dk/atira/pure/researchoutput/openaccesspermission/indeterminate"
        }
      ],
      "visibility": [
        {
          "value": "Public - No restriction",
          "key": "FREE"
        }
      ],
      "workflow": [
        {
          "value": "Validated",
          "workflowStep": "approved"
        }
      ],
      "publicationStatuses": [
        {
          "current": true,
          "publicationDate": {
            "year": 2010,
            "month": 5,
            "day": 1
          },
          "publicationStatus": [
            {
              "value": "Published",
              "pureId": 798,
              "uri": "/dk/atira/pure/researchoutput/status/published"
            }
          ]
        }
      ],
      "personAssociations": [
        {
          "pureId": 34584492,
          "externalPerson": {
            "uuid": "ecb566f9-78fe-4f6c-9dae-34be37fbc3a0",
            "name": [
              {
                "value": "Thirdpub A. Firstauthor"
              }
            ],
            "type": [
              {
                "value": "External person",
                "pureId": 4855,
                "uri": "/dk/atira/pure/externalperson/externalpersontypes/externalperson/externalperson"
              }
            ]
          },
          "name": {
            "firstName": "Thirdpub A.",
            "lastName": "Firstauthor"
          },
          "personRole": [
            {
              "value": "Author",
              "pureId": 4891,
              "uri": "/dk/atira/pure/researchoutput/roles/contributiontojournal/author"
            }
          ],
          "externalOrganisations": [
            {
              "uuid": "d5fdfca2-a581-4641-a0e4-89fedbf60cb0",
              "name": [
                {
                  "value": "University of Alberta"
                }
              ],
              "type": [
                {
                  "value": "Academic",
                  "pureId": 3438682,
                  "uri": "/dk/atira/pure/ueoexternalorganisation/ueoexternalorganisationtypes/ueoexternalorganisation/academic"
                }
              ]
            }
          ]
        },
        {
          "pureId": 34584493,
          "person": {
            "uuid": "82195bc6-c5cd-479e-b6f8-545f0f0555ba",
            "name": [
              {
                "value": "Thirdpub Secondauthor"
              }
            ]
          },
          "name": {
            "firstName": "Thirdpub",
            "lastName": "Secondauthor"
          },
          "personRole": [
            {
              "value": "Author",
              "pureId": 4891,
              "uri": "/dk/atira/pure/researchoutput/roles/contributiontojournal/author"
            }
          ],
          "organisationalUnits": [
            {
              "uuid": "937d604c-a16a-499d-80eb-bd6f931a343c",
              "name": [
                {
                  "value": "School of Science (Behrend)"
                }
              ],
              "type": [
                {
                  "value": "Department",
                  "pureId": 855,
                  "uri": "/dk/atira/pure/organisation/organisationtypes/organisation/department"
                }
              ]
            }
          ]
        },
        {
          "pureId": 34584495,
          "externalPerson": {
            "uuid": "2810a42a-2827-48e0-bae7-01f9c996ab97",
            "name": [
              {
                "value": "Thirdpub Thirdauthor"
              }
            ],
            "type": [
              {
                "value": "External person",
                "pureId": 4855,
                "uri": "/dk/atira/pure/externalperson/externalpersontypes/externalperson/externalperson"
              }
            ]
          },
          "name": {
            "firstName": "Thirdpub",
            "lastName": "Thirdauthor"
          },
          "personRole": [
            {
              "value": "Author",
              "pureId": 4891,
              "uri": "/dk/atira/pure/researchoutput/roles/contributiontojournal/author"
            }
          ]
        },
        {
          "pureId": 34584496,
          "externalPerson": {
            "uuid": "847c73a6-22c8-47e1-8433-db53204e39f5",
            "name": [
              {
                "value": "Thirdpub Fourthauthor"
              }
            ],
            "type": [
              {
                "value": "External person",
                "pureId": 4855,
                "uri": "/dk/atira/pure/externalperson/externalpersontypes/externalperson/externalperson"
              }
            ]
          },
          "name": {
            "firstName": "Thirdpub",
            "lastName": "Fourthauthor"
          },
          "personRole": [
            {
              "value": "Author",
              "pureId": 4891,
              "uri": "/dk/atira/pure/researchoutput/roles/contributiontojournal/author"
            }
          ],
          "externalOrganisations": [
            {
              "uuid": "c8f56b7a-fecd-4af5-9dff-112b0eaf7883",
              "name": [
                {
                  "value": "Duke University"
                }
              ],
              "type": [
                {
                  "value": "Academic",
                  "pureId": 3438682,
                  "uri": "/dk/atira/pure/ueoexternalorganisation/ueoexternalorganisationtypes/ueoexternalorganisation/academic"
                }
              ]
            }
          ]
        },
        {
          "pureId": 34584497,
          "externalPerson": {
            "uuid": "6810486e-4dcf-4c8f-b820-ba55546693e4",
            "name": [
              {
                "value": "Thirdpub Fifthauthor"
              }
            ],
            "type": [
              {
                "value": "External person",
                "pureId": 4855,
                "uri": "/dk/atira/pure/externalperson/externalpersontypes/externalperson/externalperson"
              }
            ]
          },
          "name": {
            "firstName": "Thirdpub",
            "lastName": "Fifthauthor"
          },
          "personRole": [
            {
              "value": "Author",
              "pureId": 4891,
              "uri": "/dk/atira/pure/researchoutput/roles/contributiontojournal/author"
            }
          ],
          "externalOrganisations": [
            {
              "uuid": "c8f56b7a-fecd-4af5-9dff-112b0eaf7883",
              "name": [
                {
                  "value": "Duke University"
                }
              ],
              "type": [
                {
                  "value": "Academic",
                  "pureId": 3438682,
                  "uri": "/dk/atira/pure/ueoexternalorganisation/ueoexternalorganisationtypes/ueoexternalorganisation/academic"
                }
              ]
            }
          ]
        }
      ],
      "organisationalUnits": [
        {
          "uuid": "937d604c-a16a-499d-80eb-bd6f931a343c",
          "name": [
            {
              "value": "School of Science (Behrend)"
            }
          ],
          "type": [
            {
              "value": "Department",
              "pureId": 855,
              "uri": "/dk/atira/pure/organisation/organisationtypes/organisation/department"
            }
          ]
        }
      ],
      "externalOrganisations": [
        {
          "uuid": "d5fdfca2-a581-4641-a0e4-89fedbf60cb0",
          "name": [
            {
              "value": "University of Alberta"
            }
          ],
          "type": [
            {
              "value": "Academic",
              "pureId": 3438682,
              "uri": "/dk/atira/pure/ueoexternalorganisation/ueoexternalorganisationtypes/ueoexternalorganisation/academic"
            }
          ]
        },
        {
          "uuid": "c8f56b7a-fecd-4af5-9dff-112b0eaf7883",
          "name": [
            {
              "value": "Duke University"
            }
          ],
          "type": [
            {
              "value": "Academic",
              "pureId": 3438682,
              "uri": "/dk/atira/pure/ueoexternalorganisation/ueoexternalorganisationtypes/ueoexternalorganisation/academic"
            }
          ]
        }
      ],
      "electronicVersions": [
        {
          "pureId": 9517634,
          "visibleOnPortalDate": "2017-01-10T21:31:33.124+0000",
          "doi": "https://doi.org/10.1080/02724631003758060",
          "accessType": [
            {
              "value": "Unknown",
              "pureId": 20055478,
              "uri": "/dk/atira/pure/core/openaccesspermission/unknown"
            }
          ],
          "versionType": [
            {
              "value": "Draft",
              "pureId": 3436203,
              "uri": "/dk/atira/pure/researchoutput/electronicversion/versiontype/publishersversion"
            }
          ]
        }
      ],
      "additionalLinks": [
        {
          "pureId": 9517637,
          "url": "http://www.scopus.com/inward/record.url?scp=77953800538&partnerID=8YFLogxK",
          "description": [
            {
              "value": "Link to publication in Scopus"
            }
          ],
          "linkType": [
            {
              "value": "Scopus publication",
              "pureId": 3436191,
              "uri": "/dk/atira/pure/links/researchoutput/scopuspublication"
            }
          ]
        },
        {
          "pureId": 9517638,
          "url": "http://www.scopus.com/inward/citedby.url?scp=77953800538&partnerID=8YFLogxK",
          "description": [
            {
              "value": "Link to citation list in Scopus"
            }
          ],
          "linkType": [
            {
              "value": "Scopus citations",
              "pureId": 3436193,
              "uri": "/dk/atira/pure/links/researchoutput/scopuscitations"
            }
          ]
        }
      ],
      "keywordGroups": [
        {
          "pureId": 9517635,
          "logicalName": "ASJCSubjectAreas",
          "type": [
            {
              "value": "All Science Journal Classification (ASJC) codes",
              "uri": "/dk/atira/pure/subjectarea/asjc"
            }
          ],
          "keywords": [
            {
              "value": "Palaeontology",
              "uri": "/dk/atira/pure/subjectarea/asjc/1900/1911"
            }
          ]
        }
      ],
      "scopusMetrics": [
        {
          "value": 1,
          "year": 2018
        },
        {
          "value": 3,
          "year": 2017
        },
        {
          "value": 7,
          "year": 2016
        },
        {
          "value": 4,
          "year": 2015
        },
        {
          "value": 3,
          "year": 2014
        },
        {
          "value": 5,
          "year": 2013
        },
        {
          "value": 3,
          "year": 2012
        },
        {
          "value": 4,
          "year": 2011
        },
        {
          "value": 2,
          "year": 2010
        }
      ]
    }
  ]
}